easycodefpy/__init__.py
easycodefpy/connector.py
easycodefpy/easycodefpy.py
easycodefpy/message.py
easycodefpy/properties.py
easycodefpy/util.py
tests/__init__.py
tests/helper.py
tests/test_connector.py
tests/test_easycodefpy.py
tests/test_properties.py
tests/test_util.py
easycodefpy-1.0.1.dist-info/LICENSE
easycodefpy-1.0.1.dist-info/METADATA
easycodefpy-1.0.1.dist-info/WHEEL
easycodefpy-1.0.1.dist-info/top_level.txt
easycodefpy-1.0.1.dist-info/RECORD
