Metadata-Version: 2.1
Name: easycodefpy
Version: 1.0.1
Summary: Easily develop codef api
Home-page: https://github.com/codef-io/easycodefpy.git
Author: CODEF
Author-email: codef.io.dev@gmail.com
License: UNKNOWN
Keywords: easycodef,codef,codef-api,codef-py,codef-python
Platform: UNKNOWN
Classifier: Programming Language :: Python :: 3.7
Classifier: License :: OSI Approved :: MIT License
Classifier: Operating System :: OS Independent
Requires-Python: >=3.5
Requires-Dist: pycryptodome (>=3.9.8)
Requires-Dist: requests (>=2.24.0)
